liscopelens/__init__.py
liscopelens/api/__init__.py
liscopelens/api/base.py
liscopelens/api/library.py
liscopelens/api/scancode.py
liscopelens/app.py
liscopelens/checker.py
liscopelens/config/default.toml
liscopelens/config/edge_example.toml
liscopelens/config/hvigor.toml
liscopelens/config/no_action.toml
liscopelens/config/user_config.toml
liscopelens/constants.py
liscopelens/infer.py
liscopelens/models/hvigor/__init__.py
liscopelens/models/hvigor/parser.py
liscopelens/models/hvigor/ver5.py
liscopelens/parser/__init__.py
liscopelens/parser/base.py
liscopelens/parser/clang/__init__.py
liscopelens/parser/clang/entry.py
liscopelens/parser/clang/gn.py
liscopelens/parser/clang/inspect.py
liscopelens/parser/compatible.py
liscopelens/parser/decycle.py
liscopelens/parser/exception.py
liscopelens/parser/inspector/__init__.py
liscopelens/parser/inspector/echo.py
liscopelens/parser/inspector/entry.py
liscopelens/parser/inspector/query.py
liscopelens/parser/inspector/styles/graph_visualizer.css
liscopelens/parser/propagate.py
liscopelens/parser/scancode.py
liscopelens/resources/exceptions/Autoconf-exception-2.0.toml
liscopelens/resources/exceptions/Bison-exception-2.2.toml
liscopelens/resources/exceptions/Classpath-exception-2.0.toml
liscopelens/resources/exceptions/Linux-syscall-note.toml
liscopelens/resources/exceptions/LLVM-exception.toml
liscopelens/resources/exceptions/SANE-exception.toml
liscopelens/resources/licenses/0BSD.toml
liscopelens/resources/licenses/4.3-BSD.toml
liscopelens/resources/licenses/AAL.toml
liscopelens/resources/licenses/AFL-3.0.toml
liscopelens/resources/licenses/AGPL-3.0-only.toml
liscopelens/resources/licenses/Apache-1.0.toml
liscopelens/resources/licenses/Apache-2.0.toml
liscopelens/resources/licenses/APL-1.0.toml
liscopelens/resources/licenses/APSL-2.0.toml
liscopelens/resources/licenses/Artistic-2.0.toml
liscopelens/resources/licenses/Beerware.toml
liscopelens/resources/licenses/BitTorrent-1.1.toml
liscopelens-0.2.15.dist-info/entry_points.txt
liscopelens-0.2.15.dist-info/LICENSE
liscopelens-0.2.15.dist-info/METADATA
liscopelens-0.2.15.dist-info/WHEEL
liscopelens-0.2.15.dist-info/RECORD
