Metadata-Version: 2.3
Name: liscopelens
Version: 0.2.15
Summary: A tool to analyze the compatibility of licenses in a project.
Author: ZION
Author-email: liuza20@lzu.edu.cn
Requires-Python: >=3.11,<=3.14
Classifier: Programming Language :: Python :: 3
Classifier: Programming Language :: Python :: 3.11
Classifier: Programming Language :: Python :: 3.12
Classifier: Programming Language :: Python :: 3.13
Requires-Dist: json5 (>=0.12.0,<0.13.0)
Requires-Dist: networkx (>=3.2.1,<4.0.0)
Requires-Dist: platformdirs (>=4.0.0,<5.0.0)
Requires-Dist: pydantic (>=2.11.7,<3.0.0)
Requires-Dist: requests (>=2.31.0,<3.0.0)
Requires-Dist: rich (>=14.0.0,<15.0.0)
Requires-Dist: textual (>=3.0.1,<4.0.0)
Requires-Dist: toml (>=0.10.2,<0.11.0)
Requires-Dist: tree-sitter (>=0.25.1,<0.26.0)
Requires-Dist: tree-sitter-cpp (>=0.23.4,<0.24.0)
